{
  "object": "Math Clay Study.013",
  "type": "MESH",
  "bbox": {
    "min": [
      -29.878747940063477,
      -29.878747940063477,
      -29.878747940063477
    ],
    "max": [
      29.878746032714844,
      29.878747940063477,
      29.878747940063477
    ]
  },
  "verts": 87095,
  "faces": 85386,
  "materials": [
    "visuals"
  ],
  "evaluated_materials": [
    "Filament and Cross Section 1OCT2024"
  ],
  "evaluated_material_faces": {
    "Filament and Cross Section 1OCT2024": 85386
  },
  "engine": "BLENDER_EEVEE",
  "authored_material": true,
  "geometry_nodes_only": true,
  "authored_light_scale": 21.894537754025826,
  "workbench_shadows": null,
  "workbench_cavity": null,
  "debug_material_output": null
}
